sqlite_utils_ml/__init__.py
sqlite_utils_ml/py.typed
sqlite_utils_ml-0.1.0.dist-info/LICENSE
sqlite_utils_ml-0.1.0.dist-info/METADATA
sqlite_utils_ml-0.1.0.dist-info/WHEEL
sqlite_utils_ml-0.1.0.dist-info/entry_points.txt
sqlite_utils_ml-0.1.0.dist-info/RECORD
