Metadata-Version: 2.1
Name: sqlite-utils-ml
Version: 0.1.0
Summary: An sqlite-utils plugin to perform machine-learning workloads
License: Apache License, Version 2.0
Author: Romain Clement
Author-email: git@romain-clement.net
Requires-Python: >=3.8.1,<4.0.0
Classifier: License :: Other/Proprietary License
Classifier: Programming Language :: Python :: 3
Classifier: Programming Language :: Python :: 3.9
Classifier: Programming Language :: Python :: 3.10
Classifier: Programming Language :: Python :: 3.11
Requires-Dist: sqlite-ml (>=0.1.2,<0.2.0)
Requires-Dist: sqlite-utils (>=3.34,<4.0)
